ShangzhaoZiDeJiemiRumenJiaoxue/README.md
ShangzhaoZiDeJiemiRumenJiaoxue/__init__.py
ShangzhaoZiDeJiemiRumenJiaoxue/__main__.py
ShangzhaoZiDeJiemiRumenJiaoxue/file.epub
ShangzhaoZiDeJiemiRumenJiaoxue/index.html
ShangzhaoZiDeJiemiRumenJiaoxue/css/__init__.py
ShangzhaoZiDeJiemiRumenJiaoxue/css/annotations.css
ShangzhaoZiDeJiemiRumenJiaoxue/css/main.css
ShangzhaoZiDeJiemiRumenJiaoxue/css/normalize.css
ShangzhaoZiDeJiemiRumenJiaoxue/css/popup.css
ShangzhaoZiDeJiemiRumenJiaoxue/font/__init__.py
ShangzhaoZiDeJiemiRumenJiaoxue/font/fontello.eot
ShangzhaoZiDeJiemiRumenJiaoxue/font/fontello.svg
ShangzhaoZiDeJiemiRumenJiaoxue/font/fontello.ttf
ShangzhaoZiDeJiemiRumenJiaoxue/font/fontello.woff
ShangzhaoZiDeJiemiRumenJiaoxue/img/__init__.py
ShangzhaoZiDeJiemiRumenJiaoxue/img/annotator-glyph-sprite.png
ShangzhaoZiDeJiemiRumenJiaoxue/img/annotator-icon-sprite.png
ShangzhaoZiDeJiemiRumenJiaoxue/img/apple-touch-icon.png
ShangzhaoZiDeJiemiRumenJiaoxue/img/cancelfullscreen.png
ShangzhaoZiDeJiemiRumenJiaoxue/img/close.png
ShangzhaoZiDeJiemiRumenJiaoxue/img/fullscreen.png
ShangzhaoZiDeJiemiRumenJiaoxue/img/loader.gif
ShangzhaoZiDeJiemiRumenJiaoxue/img/menu-icon.png
ShangzhaoZiDeJiemiRumenJiaoxue/img/save.png
ShangzhaoZiDeJiemiRumenJiaoxue/img/saved.png
ShangzhaoZiDeJiemiRumenJiaoxue/img/settings-s.png
ShangzhaoZiDeJiemiRumenJiaoxue/img/settings.png
ShangzhaoZiDeJiemiRumenJiaoxue/img/star.png
ShangzhaoZiDeJiemiRumenJiaoxue/js/__init__.py
ShangzhaoZiDeJiemiRumenJiaoxue/js/epub.js
ShangzhaoZiDeJiemiRumenJiaoxue/js/epub.min.js
ShangzhaoZiDeJiemiRumenJiaoxue/js/epub.min.map
ShangzhaoZiDeJiemiRumenJiaoxue/js/hooks.min.js
ShangzhaoZiDeJiemiRumenJiaoxue/js/hooks.min.map
ShangzhaoZiDeJiemiRumenJiaoxue/js/reader.js
ShangzhaoZiDeJiemiRumenJiaoxue/js/reader.js.map
ShangzhaoZiDeJiemiRumenJiaoxue/js/reader.min.js
ShangzhaoZiDeJiemiRumenJiaoxue/js/reader.min.map
ShangzhaoZiDeJiemiRumenJiaoxue/js/hooks/__init__.py
ShangzhaoZiDeJiemiRumenJiaoxue/js/hooks/extensions/__init__.py
shangzhao_zi_de_jiemi_rumen_jiaoxue-2024.3.2.0.dist-info/METADATA
shangzhao_zi_de_jiemi_rumen_jiaoxue-2024.3.2.0.dist-info/WHEEL
shangzhao_zi_de_jiemi_rumen_jiaoxue-2024.3.2.0.dist-info/entry_points.txt
shangzhao_zi_de_jiemi_rumen_jiaoxue-2024.3.2.0.dist-info/top_level.txt
shangzhao_zi_de_jiemi_rumen_jiaoxue-2024.3.2.0.dist-info/RECORD
